activation_extractor/__init__.py
activation_extractor/__main__.py
activation_extractor/extractors/intermediateExtractor.py
activation_extractor/extractors/intermediateExtractorBase.py
activation_extractor/inferencers/inferencer.py
activation_extractor/model_functions/default_hooked_layers.py
activation_extractor/model_functions/inference_funs.py
activation_extractor/model_functions/load_models.py
activation_extractor/model_functions/model_types.py
activation_extractor/model_functions/tokenize_funs.py
activation_extractor-0.0.0.dist-info/LICENSE
activation_extractor-0.0.0.dist-info/METADATA
activation_extractor-0.0.0.dist-info/WHEEL
activation_extractor-0.0.0.dist-info/entry_points.txt
activation_extractor-0.0.0.dist-info/top_level.txt
activation_extractor-0.0.0.dist-info/RECORD
