Metadata-Version: 2.1
Name: activation_extractor
Version: 0.0.0
Summary: Extracting intermediate activations/embeddings from any Pytorch model
Author-email: Edith Villegas <edith.villegas@areasciencepark.it>
License: MIT License
Project-URL: repository, https://github.com/edithvillegas/activation-extractor
Project-URL: documentation, https://github.com/edithvillegas/activation-extractor
Keywords: deep-learning,pytorch,nlp
Classifier: License :: OSI Approved :: MIT License
Classifier: Programming Language :: Python
Classifier: Programming Language :: Python :: 3
Requires-Python: >=3.10
License-File: LICENSE
Requires-Dist: numpy
Requires-Dist: torch
Requires-Dist: transformers
Requires-Dist: datasets
Provides-Extra: build
Provides-Extra: dev
Requires-Dist: bumpver ; extra == 'dev'
Requires-Dist: pytest ; extra == 'dev'
